boolean_question/__init__.py
boolean_question/boolq.py
boolean_question/utils/__init__.py
boolean_question/utils/helper.py
boolean_question-0.0.3.dist-info/LICENSE
boolean_question-0.0.3.dist-info/METADATA
boolean_question-0.0.3.dist-info/WHEEL
boolean_question-0.0.3.dist-info/top_level.txt
boolean_question-0.0.3.dist-info/RECORD
