Metadata-Version: 2.1
Name: boolean-question
Version: 0.0.3
Summary: Boolean question-answer prediction with AI
Home-page: https://github.com/Saadmairaj/boolean-question
Author: Saad Mairaj
Author-email: Saadmairaj@yahoo.in
License: Apache
Project-URL: Bug Reports, https://github.com/Saadmairaj/boolean-question/issues
Project-URL: Source, https://github.com/Saadmairaj/boolean-question
Project-URL: Ask Question, https://github.com/Saadmairaj/boolean-question/discussions
Keywords: question-answer,nlp,pytorch,AI,artificial-intelligence,deep-learning,natural-language-processing
Platform: UNKNOWN
Classifier: Development Status :: 5 - Production/Stable
Classifier: Intended Audience :: Developers
Classifier: Intended Audience :: Education
Classifier: Intended Audience :: Science/Research
Classifier: Operating System :: OS Independent
Classifier: Programming Language :: Python :: 3
Classifier: Programming Language :: Python :: 3.7
Classifier: Programming Language :: Python :: 3.8
Classifier: Programming Language :: Python :: 3.9
Classifier: Topic :: Scientific/Engineering :: Artificial Intelligence
Classifier: License :: OSI Approved :: Apache Software License
Requires-Python: >=3
Requires-Dist: gdown (==3.13.0)
Requires-Dist: torch (==1.9.0)
Requires-Dist: torchvision (==0.10.0)
Requires-Dist: transformers (==2.5.1)
Requires-Dist: pandas (==1.3.1)
Requires-Dist: numpy (==1.21.1)
